anovable/__init__.py
anovable/_version.py
anovable/cli.py
anovable/client.py
anovable/config.py
anovable/constants.py
anovable/exceptions.py
anovable/models.py
matonb_anovable-1.5.0.dist-info/METADATA
matonb_anovable-1.5.0.dist-info/WHEEL
matonb_anovable-1.5.0.dist-info/entry_points.txt
matonb_anovable-1.5.0.dist-info/licenses/LICENSE
matonb_anovable-1.5.0.dist-info/RECORD
