Metadata-Version: 2.4
Name: matonb-anovable
Version: 1.5.0
Summary: Python library for controlling Anova Precision Cookers via Bluetooth LE
Project-URL: Homepage, https://github.com/matonb/anovable
Project-URL: Repository, https://github.com/matonb/anovable
Project-URL: Issues, https://github.com/matonb/anovable/issues
Author-email: matonb <matonb@users.noreply.github.com>
License: MIT
License-File: LICENSE
Keywords: anova,ble,bluetooth,precision-cooker,sous-vide
Classifier: Development Status :: 5 - Production/Stable
Classifier: Intended Audience :: Developers
Classifier: License :: OSI Approved :: MIT License
Classifier: Operating System :: OS Independent
Classifier: Programming Language :: Python :: 3
Classifier: Programming Language :: Python :: 3.8
Classifier: Programming Language :: Python :: 3.9
Classifier: Programming Language :: Python :: 3.10
Classifier: Programming Language :: Python :: 3.11
Classifier: Programming Language :: Python :: 3.12
Classifier: Topic :: Communications
Classifier: Topic :: Home Automation
Classifier: Topic :: Software Development :: Libraries :: Python Modules
Classifier: Topic :: System :: Networking
Requires-Python: >=3.8
Requires-Dist: bleak>=0.20.0
Requires-Dist: pyyaml>=6.0
Requires-Dist: typer>=0.9.0
Provides-Extra: dev
Requires-Dist: mypy>=1.0.0; extra == 'dev'
Requires-Dist: pre-commit>=3.0.0; extra == 'dev'
Requires-Dist: pytest-asyncio>=0.21.0; extra == 'dev'
Requires-Dist: pytest-cov>=4.0.0; extra == 'dev'
Requires-Dist: pytest>=7.0.0; extra == 'dev'
Requires-Dist: ruff>=0.1.0; extra == 'dev'
Requires-Dist: types-pyyaml>=6.0.0; extra == 'dev'
